bingtiles/__init__.py
bingtiles/__main__.py
bingtiles/fetch.py
bingtiles/mapgen.py
bingtiles/utils.py
bingtiles/provider/__init__.py
bingtiles/provider/bing.py
bingtiles/provider/esri.py
bingtiles/provider/google.py
bingtiles/provider/usgs.py
bingtiles-0.0.1.dist-info/LICENSE
bingtiles-0.0.1.dist-info/METADATA
bingtiles-0.0.1.dist-info/WHEEL
bingtiles-0.0.1.dist-info/entry_points.txt
bingtiles-0.0.1.dist-info/top_level.txt
bingtiles-0.0.1.dist-info/RECORD
