Metadata-Version: 2.1
Name: bingtiles
Version: 0.0.1
Summary: Small library for accessing Bing Static Maps API and alike
Author: Tolga Demirdal
License: GNU LESSER GENERAL PUBLIC LICENSE
Project-URL: Homepage, https://github.com/shadymeowy/python-drawing3d
Project-URL: Repository, https://github.com/shadymeowy/python-drawing3d
License-File: LICENSE
Requires-Dist: requests
Requires-Dist: Pillow
